ec4sap/__init__.py
ec4sap/abiquo_api.py
ec4sap/abiquo_env.py
ec4sap/cli.py
ec4sap/cms_api.py
ec4sap/cms_env.py
ec4sap/config.py
ec4sap/getVM.py
ec4sap_client-0.5.1.dist-info/LICENSE.txt
ec4sap_client-0.5.1.dist-info/METADATA
ec4sap_client-0.5.1.dist-info/WHEEL
ec4sap_client-0.5.1.dist-info/entry_points.txt
ec4sap_client-0.5.1.dist-info/top_level.txt
ec4sap_client-0.5.1.dist-info/RECORD
