Metadata-Version: 2.1
Name: ec4sap-client
Version: 0.5.1
Summary: EC4SAP Python Client
Home-page: https://gitlab.swisscloud.io/itclouds/ec4sap-python-client
Author: Christian Werder
Author-email: christian.werder@swisscom.com
License: Apache License 2.0
Platform: UNKNOWN
Classifier: Development Status :: 4 - Beta
Classifier: Intended Audience :: Developers
Classifier: Intended Audience :: System Administrators
Classifier: Programming Language :: Python :: 2.7
Classifier: License :: OSI Approved :: Apache Software License
Classifier: Operating System :: OS Independent
Requires-Dist: requests (>=2.0.0)
Requires-Dist: requests-oauthlib (>=0.4.2)
Requires-Dist: abiquo-api (>=0.1.14)
